calculator_olu_ile/__init__.py
calculator_olu_ile/calculator.py
calculator_olu_ile/customerror.py
calculator_olu_ile-0.2.1.dist-info/LICENSE
calculator_olu_ile-0.2.1.dist-info/WHEEL
calculator_olu_ile-0.2.1.dist-info/METADATA
calculator_olu_ile-0.2.1.dist-info/RECORD
