Metadata-Version: 2.1
Name: calculator_olu_ile
Version: 0.2.1
Summary: Calculator with operations add, subtract, divide, multipy and root.
Author-email: Oluwole Ilesanmi <oluwoleilesanmi@gmail.com>
Requires-Python: >=3.8
Classifier: License :: OSI Approved :: MIT License
